cursesplus/__init__.py
cursesplus/constants.py
cursesplus/cp.py
cursesplus/filedialog.py
cursesplus/messagebox.py
cursesplus/transitions.py
cursesplus/utils.py
cursesplus-3.20.1.dist-info/licenses/LICENSE
cursesplus-3.20.1.dist-info/METADATA
cursesplus-3.20.1.dist-info/WHEEL
cursesplus-3.20.1.dist-info/top_level.txt
cursesplus-3.20.1.dist-info/RECORD
