Metadata-Version: 2.4
Name: cursesplus
Version: 3.20.1
Summary: An extension program to curses that offers option menus, message boxes, file dialogues and more
Author-email: Enderbyte Programs <enderbyte09@gmail.com>
Project-URL: Homepage, https://github.com/Enderbyte-Programs/Curses-Plus
Project-URL: Bug Tracker, https://github.com/Enderbyte-Programs/Curses-Plus/issues
Classifier: Programming Language :: Python :: 3
Classifier: License :: OSI Approved :: MIT License
Classifier: Operating System :: OS Independent
Requires-Python: >=3.6
License-File: LICENSE
Dynamic: license-file
